<annotation>
	<folder></folder>
	<filename>IMG01745_JPG.rf.ef8858450d9e2aac0af85a05e3e33c9f.jpg</filename>
	<path>IMG01745_JPG.rf.ef8858450d9e2aac0af85a05e3e33c9f.jpg</path>
	<source>
		<database>roboflow.com</database>
	</source>
	<size>
		<width>3264</width>
		<height>1840</height>
		<depth>3</depth>
	</size>
	<segmented>0</segmented>
	<object>
		<name>dead</name>
		<pose>Unspecified</pose>
		<truncated>0</truncated>
		<difficult>0</difficult>
		<occluded>0</occluded>
		<bndbox>
			<xmin>1443</xmin>
			<xmax>1555</xmax>
			<ymin>952</ymin>
			<ymax>1074</ymax>
		</bndbox>
		<polygon>
			<x1>1448</x1>
			<y1>1021</y1>
			<x2>1459</x2>
			<y2>1036</y2>
			<x3>1494</x3>
			<y3>1067</y3>
			<x4>1509</x4>
			<y4>1073</y4>
			<x5>1521</x5>
			<y5>1072</y5>
			<x6>1538</x6>
			<y6>1063</y6>
			<x7>1550</x7>
			<y7>1050</y7>
			<x8>1554</x8>
			<y8>1038</y8>
			<x9>1548</x9>
			<y9>1002</y9>
			<x10>1536</x10>
			<y10>976</y10>
			<x11>1521</x11>
			<y11>958</y11>
			<x12>1504</x12>
			<y12>951</y12>
			<x13>1474</x13>
			<y13>954</y13>
			<x14>1459</x14>
			<y14>963</y14>
			<x15>1446</x15>
			<y15>980</y15>
			<x16>1442</x16>
			<y16>1003</y16>
			<x17>1448</x17>
			<y17>1021</y17>
		</polygon>
	</object>
	<object>
		<name>dead</name>
		<pose>Unspecified</pose>
		<truncated>0</truncated>
		<difficult>0</difficult>
		<occluded>0</occluded>
		<bndbox>
			<xmin>1644</xmin>
			<xmax>1729</xmax>
			<ymin>1407</ymin>
			<ymax>1533</ymax>
		</bndbox>
		<polygon>
			<x1>1659</x1>
			<y1>1520</y1>
			<x2>1664</x2>
			<y2>1527</y2>
			<x3>1675</x3>
			<y3>1532</y3>
			<x4>1702</x4>
			<y4>1527</y4>
			<x5>1716</x5>
			<y5>1514</y5>
			<x6>1728</x6>
			<y6>1491</y6>
			<x7>1727</x7>
			<y7>1469</y7>
			<x8>1716</x8>
			<y8>1443</y8>
			<x9>1700</x9>
			<y9>1424</y9>
			<x10>1677</x10>
			<y10>1406</y10>
			<x11>1651</x11>
			<y11>1419</y11>
			<x12>1643</x12>
			<y12>1433</y12>
			<x13>1643</x13>
			<y13>1484</y13>
			<x14>1659</x14>
			<y14>1520</y14>
		</polygon>
	</object>
	<object>
		<name>dead</name>
		<pose>Unspecified</pose>
		<truncated>0</truncated>
		<difficult>0</difficult>
		<occluded>0</occluded>
		<bndbox>
			<xmin>3097</xmin>
			<xmax>3197</xmax>
			<ymin>1123</ymin>
			<ymax>1234</ymax>
		</bndbox>
		<polygon>
			<x1>3103</x1>
			<y1>1188</y1>
			<x2>3117</x2>
			<y2>1211</y2>
			<x3>3133</x3>
			<y3>1226</y3>
			<x4>3143</x4>
			<y4>1232</y4>
			<x5>3158</x5>
			<y5>1233</y5>
			<x6>3182</x6>
			<y6>1224</y6>
			<x7>3193</x7>
			<y7>1203</y7>
			<x8>3196</x8>
			<y8>1168</y8>
			<x9>3174</x9>
			<y9>1131</y9>
			<x10>3156</x10>
			<y10>1122</y10>
			<x11>3128</x11>
			<y11>1122</y11>
			<x12>3104</x12>
			<y12>1135</y12>
			<x13>3096</x13>
			<y13>1150</y13>
			<x14>3096</x14>
			<y14>1169</y14>
			<x15>3103</x15>
			<y15>1188</y15>
		</polygon>
	</object>
	<object>
		<name>live</name>
		<pose>Unspecified</pose>
		<truncated>0</truncated>
		<difficult>0</difficult>
		<occluded>0</occluded>
		<bndbox>
			<xmin>1981</xmin>
			<xmax>2112</xmax>
			<ymin>802</ymin>
			<ymax>925</ymax>
		</bndbox>
		<polygon>
			<x1>2001</x1>
			<y1>880</y1>
			<x2>2007</x2>
			<y2>910</y2>
			<x3>2042</x3>
			<y3>924</y3>
			<x4>2061</x4>
			<y4>920</y4>
			<x5>2084</x5>
			<y5>899</y5>
			<x6>2111</x6>
			<y6>846</y6>
			<x7>2110</x7>
			<y7>831</y7>
			<x8>2098</x8>
			<y8>801</y8>
			<x9>2044</x9>
			<y9>801</y9>
			<x10>2011</x10>
			<y10>807</y10>
			<x11>1991</x11>
			<y11>816</y11>
			<x12>1980</x12>
			<y12>831</y12>
			<x13>1981</x13>
			<y13>864</y13>
			<x14>2001</x14>
			<y14>880</y14>
		</polygon>
	</object>
	<metadata>
	</metadata>
</annotation>
