<annotation>
	<folder></folder>
	<filename>IMG01817_JPG.rf.5ab0761df62697806c51f7d7191f19b2.jpg</filename>
	<path>IMG01817_JPG.rf.5ab0761df62697806c51f7d7191f19b2.jpg</path>
	<source>
		<database>roboflow.com</database>
	</source>
	<size>
		<width>3264</width>
		<height>1840</height>
		<depth>3</depth>
	</size>
	<segmented>0</segmented>
	<object>
		<name>dead</name>
		<pose>Unspecified</pose>
		<truncated>0</truncated>
		<difficult>0</difficult>
		<occluded>0</occluded>
		<bndbox>
			<xmin>996</xmin>
			<xmax>1092</xmax>
			<ymin>988</ymin>
			<ymax>1077</ymax>
		</bndbox>
		<polygon>
			<x1>999</x1>
			<y1>1056</y1>
			<x2>1026</x2>
			<y2>1076</y2>
			<x3>1067</x3>
			<y3>1063</y3>
			<x4>1091</x4>
			<y4>1045</y4>
			<x5>1088</x5>
			<y5>1038</y5>
			<x6>1077</x6>
			<y6>1031</y6>
			<x7>1058</x7>
			<y7>999</y7>
			<x8>1040</x8>
			<y8>987</y8>
			<x9>1006</x9>
			<y9>1002</y9>
			<x10>999</x10>
			<y10>1009</y10>
			<x11>996</x11>
			<y11>1021</y11>
			<x12>995</x12>
			<y12>1043</y12>
			<x13>999</x13>
			<y13>1056</y13>
		</polygon>
	</object>
	<object>
		<name>dead</name>
		<pose>Unspecified</pose>
		<truncated>0</truncated>
		<difficult>0</difficult>
		<occluded>0</occluded>
		<bndbox>
			<xmin>961</xmin>
			<xmax>1087</xmax>
			<ymin>1087</ymin>
			<ymax>1189</ymax>
		</bndbox>
		<polygon>
			<x1>990</x1>
			<y1>1166</y1>
			<x2>1003</x2>
			<y2>1184</y2>
			<x3>1013</x3>
			<y3>1188</y3>
			<x4>1054</x4>
			<y4>1167</y4>
			<x5>1086</x5>
			<y5>1139</y5>
			<x6>1076</x6>
			<y6>1127</y6>
			<x7>1057</x7>
			<y7>1118</y7>
			<x8>1048</x8>
			<y8>1109</y8>
			<x9>1039</x9>
			<y9>1086</y9>
			<x10>1016</x10>
			<y10>1095</y10>
			<x11>960</x11>
			<y11>1132</y11>
			<x12>961</x12>
			<y12>1146</y12>
			<x13>990</x13>
			<y13>1166</y13>
		</polygon>
	</object>
	<object>
		<name>dead</name>
		<pose>Unspecified</pose>
		<truncated>0</truncated>
		<difficult>0</difficult>
		<occluded>0</occluded>
		<bndbox>
			<xmin>1124</xmin>
			<xmax>1310</xmax>
			<ymin>945</ymin>
			<ymax>1094</ymax>
		</bndbox>
		<polygon>
			<x1>1199</x1>
			<y1>982</y1>
			<x2>1136</x2>
			<y2>1000</y2>
			<x3>1133</x3>
			<y3>1004</y3>
			<x4>1123</x4>
			<y4>1002</y4>
			<x5>1137</x5>
			<y5>1009</y5>
			<x6>1142</x6>
			<y6>1021</y6>
			<x7>1141</x7>
			<y7>1037</y7>
			<x8>1124</x8>
			<y8>1053</y8>
			<x9>1123</x9>
			<y9>1060</y9>
			<x10>1166</x10>
			<y10>1084</y10>
			<x11>1180</x11>
			<y11>1077</y11>
			<x12>1192</x12>
			<y12>1093</y12>
			<x13>1208</x13>
			<y13>1064</y13>
			<x14>1309</x14>
			<y14>981</y14>
			<x15>1307</x15>
			<y15>971</y15>
			<x16>1272</x16>
			<y16>946</y16>
			<x17>1267</x17>
			<y17>944</y17>
			<x18>1253</x18>
			<y18>948</y18>
			<x19>1229</x19>
			<y19>959</y19>
			<x20>1199</x20>
			<y20>982</y20>
		</polygon>
	</object>
	<object>
		<name>dead</name>
		<pose>Unspecified</pose>
		<truncated>0</truncated>
		<difficult>0</difficult>
		<occluded>0</occluded>
		<bndbox>
			<xmin>962</xmin>
			<xmax>1092</xmax>
			<ymin>988</ymin>
			<ymax>1186</ymax>
		</bndbox>
		<polygon>
			<x1>965</x1>
			<y1>1146</y1>
			<x2>975</x2>
			<y2>1156</y2>
			<x3>994</x3>
			<y3>1166</y3>
			<x4>1002</x4>
			<y4>1182</y4>
			<x5>1011</x5>
			<y5>1185</y5>
			<x6>1039</x6>
			<y6>1177</y6>
			<x7>1064</x7>
			<y7>1161</y7>
			<x8>1074</x8>
			<y8>1136</y8>
			<x9>1091</x9>
			<y9>1131</y9>
			<x10>1089</x10>
			<y10>1125</y10>
			<x11>1049</x11>
			<y11>1106</y11>
			<x12>1046</x12>
			<y12>1081</y12>
			<x13>1072</x13>
			<y13>1060</y13>
			<x14>1066</x14>
			<y14>1043</y14>
			<x15>1070</x15>
			<y15>1030</y15>
			<x16>1064</x16>
			<y16>1010</y16>
			<x17>1050</x17>
			<y17>1004</y17>
			<x18>1039</x18>
			<y18>987</y18>
			<x19>1005</x19>
			<y19>1002</y19>
			<x20>999</x20>
			<y20>1008</y20>
			<x21>995</x21>
			<y21>1028</y21>
			<x22>1000</x22>
			<y22>1060</y22>
			<x23>1020</x23>
			<y23>1074</y23>
			<x24>1030</x24>
			<y24>1091</y24>
			<x25>1001</x25>
			<y25>1101</y25>
			<x26>962</x26>
			<y26>1131</y26>
			<x27>961</x27>
			<y27>1139</y27>
			<x28>965</x28>
			<y28>1146</y28>
		</polygon>
	</object>
	<object>
		<name>dead</name>
		<pose>Unspecified</pose>
		<truncated>0</truncated>
		<difficult>0</difficult>
		<occluded>0</occluded>
		<bndbox>
			<xmin>1647</xmin>
			<xmax>1761</xmax>
			<ymin>284</ymin>
			<ymax>393</ymax>
		</bndbox>
		<polygon>
			<x1>1662</x1>
			<y1>379</y1>
			<x2>1677</x2>
			<y2>390</y2>
			<x3>1698</x3>
			<y3>392</y3>
			<x4>1728</x4>
			<y4>382</y4>
			<x5>1751</x5>
			<y5>367</y5>
			<x6>1760</x6>
			<y6>353</y6>
			<x7>1760</x7>
			<y7>319</y7>
			<x8>1753</x8>
			<y8>303</y8>
			<x9>1740</x9>
			<y9>289</y9>
			<x10>1714</x10>
			<y10>283</y10>
			<x11>1715</x11>
			<y11>306</y11>
			<x12>1702.5</x12>
			<y12>317</y12>
			<x13>1686</x13>
			<y13>315</y13>
			<x14>1664</x14>
			<y14>299</y14>
			<x15>1646</x15>
			<y15>305</y15>
			<x16>1651</x16>
			<y16>355</y16>
			<x17>1662</x17>
			<y17>379</y17>
		</polygon>
	</object>
	<object>
		<name>live</name>
		<pose>Unspecified</pose>
		<truncated>0</truncated>
		<difficult>0</difficult>
		<occluded>0</occluded>
		<bndbox>
			<xmin>1897</xmin>
			<xmax>2035</xmax>
			<ymin>224</ymin>
			<ymax>350</ymax>
		</bndbox>
		<polygon>
			<x1>1917</x1>
			<y1>329</y1>
			<x2>1944</x2>
			<y2>348</y2>
			<x3>1961</x3>
			<y3>349</y3>
			<x4>1983</x4>
			<y4>341</y4>
			<x5>2015</x5>
			<y5>314</y5>
			<x6>2028</x6>
			<y6>289</y6>
			<x7>2034</x7>
			<y7>259</y7>
			<x8>2021</x8>
			<y8>241</y8>
			<x9>2009</x9>
			<y9>239</y9>
			<x10>1982</x10>
			<y10>225</y10>
			<x11>1944</x11>
			<y11>223</y11>
			<x12>1910</x12>
			<y12>248</y12>
			<x13>1899</x13>
			<y13>274</y13>
			<x14>1896</x14>
			<y14>299</y14>
			<x15>1917</x15>
			<y15>329</y15>
		</polygon>
	</object>
	<metadata>
	</metadata>
</annotation>
