<annotation>
	<folder></folder>
	<filename>IMG01661_JPG.rf.5f1861d171478b1fb1c66b9be9ca0e1d.jpg</filename>
	<path>IMG01661_JPG.rf.5f1861d171478b1fb1c66b9be9ca0e1d.jpg</path>
	<source>
		<database>roboflow.com</database>
	</source>
	<size>
		<width>3264</width>
		<height>1840</height>
		<depth>3</depth>
	</size>
	<segmented>0</segmented>
	<object>
		<name>dead</name>
		<pose>Unspecified</pose>
		<truncated>0</truncated>
		<difficult>0</difficult>
		<occluded>0</occluded>
		<bndbox>
			<xmin>1084</xmin>
			<xmax>1191</xmax>
			<ymin>1693</ymin>
			<ymax>1786</ymax>
		</bndbox>
		<polygon>
			<x1>1089</x1>
			<y1>1757</y1>
			<x2>1112</x2>
			<y2>1778</y2>
			<x3>1136</x3>
			<y3>1785</y3>
			<x4>1155</x4>
			<y4>1784</y4>
			<x5>1175</x5>
			<y5>1773</y5>
			<x6>1184</x6>
			<y6>1759</y6>
			<x7>1190</x7>
			<y7>1729</y7>
			<x8>1184</x8>
			<y8>1709</y8>
			<x9>1170</x9>
			<y9>1700</y9>
			<x10>1141</x10>
			<y10>1692</y10>
			<x11>1095</x11>
			<y11>1700</y11>
			<x12>1089</x12>
			<y12>1706</y12>
			<x13>1083</x13>
			<y13>1727</y13>
			<x14>1083</x14>
			<y14>1750</y14>
			<x15>1089</x15>
			<y15>1757</y15>
		</polygon>
	</object>
	<object>
		<name>dead</name>
		<pose>Unspecified</pose>
		<truncated>0</truncated>
		<difficult>0</difficult>
		<occluded>0</occluded>
		<bndbox>
			<xmin>1192</xmin>
			<xmax>1277</xmax>
			<ymin>1693</ymin>
			<ymax>1801</ymax>
		</bndbox>
		<polygon>
			<x1>1193</x1>
			<y1>1779</y1>
			<x2>1203</x2>
			<y2>1793</y2>
			<x3>1223</x3>
			<y3>1800</y3>
			<x4>1242</x4>
			<y4>1800</y4>
			<x5>1269</x5>
			<y5>1785</y5>
			<x6>1276</x6>
			<y6>1769</y6>
			<x7>1275</x7>
			<y7>1727</y7>
			<x8>1270</x8>
			<y8>1711</y8>
			<x9>1256</x9>
			<y9>1695</y9>
			<x10>1245</x10>
			<y10>1692</y10>
			<x11>1209</x11>
			<y11>1695</y11>
			<x12>1193</x12>
			<y12>1713</y12>
			<x13>1191</x13>
			<y13>1763</y13>
			<x14>1193</x14>
			<y14>1779</y14>
		</polygon>
	</object>
	<object>
		<name>live</name>
		<pose>Unspecified</pose>
		<truncated>0</truncated>
		<difficult>0</difficult>
		<occluded>0</occluded>
		<bndbox>
			<xmin>2003</xmin>
			<xmax>2115</xmax>
			<ymin>952</ymin>
			<ymax>1075</ymax>
		</bndbox>
		<polygon>
			<x1>2017</x1>
			<y1>1058</y1>
			<x2>2033</x2>
			<y2>1069</y2>
			<x3>2062</x3>
			<y3>1074</y3>
			<x4>2082</x4>
			<y4>1068</y4>
			<x5>2096</x5>
			<y5>1062</y5>
			<x6>2114</x6>
			<y6>1044</y6>
			<x7>2114</x7>
			<y7>1001</y7>
			<x8>2110</x8>
			<y8>982</y8>
			<x9>2071</x9>
			<y9>954</y9>
			<x10>2048</x10>
			<y10>951</y10>
			<x11>2036</x11>
			<y11>954</y11>
			<x12>2018</x12>
			<y12>966</y12>
			<x13>2002</x13>
			<y13>990</y13>
			<x14>2004</x14>
			<y14>1038</y14>
			<x15>2017</x15>
			<y15>1058</y15>
		</polygon>
	</object>
	<object>
		<name>live</name>
		<pose>Unspecified</pose>
		<truncated>0</truncated>
		<difficult>0</difficult>
		<occluded>0</occluded>
		<bndbox>
			<xmin>1939</xmin>
			<xmax>2041</xmax>
			<ymin>909</ymin>
			<ymax>997</ymax>
		</bndbox>
		<polygon>
			<x1>1944</x1>
			<y1>972</y1>
			<x2>1969</x2>
			<y2>991</y2>
			<x3>1988</x3>
			<y3>996</y3>
			<x4>1998</x4>
			<y4>995</y4>
			<x5>2017</x5>
			<y5>968</y5>
			<x6>2035</x6>
			<y6>955</y6>
			<x7>2040</x7>
			<y7>946</y7>
			<x8>2033</x8>
			<y8>926</y8>
			<x9>2020</x9>
			<y9>915</y9>
			<x10>2003</x10>
			<y10>908</y10>
			<x11>1992</x11>
			<y11>908</y11>
			<x12>1958</x12>
			<y12>920</y12>
			<x13>1943</x13>
			<y13>934</y13>
			<x14>1939</x14>
			<y14>944</y14>
			<x15>1938</x15>
			<y15>954</y15>
			<x16>1944</x16>
			<y16>972</y16>
		</polygon>
	</object>
	<object>
		<name>live</name>
		<pose>Unspecified</pose>
		<truncated>0</truncated>
		<difficult>0</difficult>
		<occluded>0</occluded>
		<bndbox>
			<xmin>1</xmin>
			<xmax>86</xmax>
			<ymin>877</ymin>
			<ymax>1000</ymax>
		</bndbox>
		<polygon>
			<x1>0</x1>
			<y1>999</y1>
			<x2>18</x2>
			<y2>996</y2>
			<x3>32</x3>
			<y3>987</y3>
			<x4>50</x4>
			<y4>958</y4>
			<x5>78</x5>
			<y5>948</y5>
			<x6>85</x6>
			<y6>939</y6>
			<x7>82</x7>
			<y7>922</y7>
			<x8>56</x8>
			<y8>905</y8>
			<x9>44</x9>
			<y9>888</y9>
			<x10>32</x10>
			<y10>887</y10>
			<x11>6</x11>
			<y11>876</y11>
			<x12>0</x12>
			<y12>876</y12>
			<x13>0</x13>
			<y13>999</y13>
		</polygon>
	</object>
	<metadata>
	</metadata>
</annotation>
